pyenv/__init__.py
pyenv/main.py
pyenv.command-0.0.2.dist-info/METADATA
pyenv.command-0.0.2.dist-info/WHEEL
pyenv.command-0.0.2.dist-info/top_level.txt
pyenv.command-0.0.2.dist-info/RECORD
