Metadata-Version: 2.1
Name: pyenv.command
Version: 0.0.2
Summary: Handles creation of virtual environment
Home-page: https://github.com/aiscenblue/pyenv
Author: Jeffrey Marvin Forones
Author-email: aiscenblue@gmail.com
License: UNKNOWN
Project-URL: Bug Tracker, https://github.com/aiscenblue/pyenv/issues
Platform: UNKNOWN
Classifier: Programming Language :: Python :: 3
Classifier: License :: OSI Approved :: MIT License
Classifier: Operating System :: OS Independent
Requires-Python: >=3.6
